<metadata xml:lang="en"><Esri><CreaDate>20140324</CreaDate><CreaTime>12392800</CreaTime><ArcGISFormat>1.0</ArcGISFormat><ArcGISstyle>ISO 19139 Metadata Implementation Specification</ArcGISstyle><SyncOnce>FALSE</SyncOnce><DataProperties><itemProps><itemLocation><linkage Sync="FALSE">withheld</linkage><protocol Sync="TRUE">Local Area Network</protocol></itemLocation><itemName Sync="TRUE">ports_major</itemName><nativeExtBox><westBL Sync="TRUE">-168.938200</westBL><eastBL Sync="TRUE">-66.166670</eastBL><southBL Sync="TRUE">18.001260</southBL><northBL Sync="TRUE">67.719180</northBL><exTypeCode Sync="TRUE">1</exTypeCode></nativeExtBox><itemSize Sync="TRUE">0.004</itemSize><imsContentType Sync="TRUE" export="False">002</imsContentType></itemProps><coordRef><type Sync="TRUE">Geographic</type><geogcsn Sync="TRUE">GCS_WGS_1984</geogcsn><csUnits Sync="TRUE">Angular Unit: Degree (0.017453)</csUnits><peXml Sync="TRUE">&lt;GeographicCoordinateSystem xsi:type='typens:GeographicCoordinateSystem' xmlns:xsi='http://www.w3.org/2001/XMLSchema-instance' xmlns:xs='http://www.w3.org/2001/XMLSchema' xmlns:typens='http://www.esri.com/schemas/ArcGIS/10.1'&gt;&lt;WKT&gt;GEOGCS[&amp;quot;GCS_WGS_1984&amp;quot;,DATUM[&amp;quot;D_WGS_1984&amp;quot;,SPHEROID[&amp;quot;WGS_1984&amp;quot;,6378137.0,298.257223563]],PRIMEM[&amp;quot;Greenwich&amp;quot;,0.0],UNIT[&amp;quot;Degree&amp;quot;,0.0174532925199433],METADATA[&amp;quot;World&amp;quot;,-180.0,-90.0,180.0,90.0,0.0,0.0174532925199433,0.0,1262],AUTHORITY[&amp;quot;EPSG&amp;quot;,4326]]&lt;/WKT&gt;&lt;XOrigin&gt;-400&lt;/XOrigin&gt;&lt;YOrigin&gt;-400&lt;/YOrigin&gt;&lt;XYScale&gt;11258999068426.238&lt;/XYScale&gt;&lt;ZOrigin&gt;-100000&lt;/ZOrigin&gt;&lt;ZScale&gt;10000&lt;/ZScale&gt;&lt;MOrigin&gt;-100000&lt;/MOrigin&gt;&lt;MScale&gt;10000&lt;/MScale&gt;&lt;XYTolerance&gt;8.983152841195215e-009&lt;/XYTolerance&gt;&lt;ZTolerance&gt;0.001&lt;/ZTolerance&gt;&lt;MTolerance&gt;0.001&lt;/MTolerance&gt;&lt;HighPrecision&gt;true&lt;/HighPrecision&gt;&lt;LeftLongitude&gt;-180&lt;/LeftLongitude&gt;&lt;WKID&gt;4326&lt;/WKID&gt;&lt;LatestWKID&gt;4326&lt;/LatestWKID&gt;&lt;/GeographicCoordinateSystem&gt;</peXml></coordRef></DataProperties><SyncDate>20140410</SyncDate><SyncTime>07410200</SyncTime><ModDate>20140416</ModDate><ModTime>14031800</ModTime><ArcGISProfile>ISO19139</ArcGISProfile><scaleRange><minScale>150000000</minScale><maxScale>5000</maxScale></scaleRange></Esri><mdLang><languageCode value="eng"/><countryCode value="USA" Sync="TRUE"/></mdLang><mdChar><CharSetCd value="004"/></mdChar><mdHrLv><ScopeCd value="005"/></mdHrLv><mdContact xmlns=""><rpIndName>Waterborne Commerce Statistics Center</rpIndName><rpOrgName>US Army Corps of Engineers</rpOrgName><rpCntInfo><cntAddress addressType="both"><city>Vicksburg</city><adminArea>MS</adminArea><country>US</country></cntAddress></rpCntInfo><role><RoleCd value="007"/></role></mdContact><mdDateSt Sync="TRUE">20140416</mdDateSt><mdStanName>ArcGIS Metadata</mdStanName><mdStanVer>1.0</mdStanVer><distInfo xmlns=""><distributor xmlns=""><distorCont><rpIndName>Waterborne Commerce Statistics Center</rpIndName><rpOrgName>US Army Corps of Engineers</rpOrgName><rpCntInfo><cntPhone><voiceNum tddtty="">504-862-1426 or 504-862-1441</voiceNum></cntPhone><cntAddress addressType=""><delPoint>PO BOX 61280</delPoint><city>New Orleans,</city><adminArea>LA</adminArea><postCode>70161-1280</postCode><eMailAdd>CEIWR-NDCWCSC.WEBMASTER@usace.army.mil</eMailAdd></cntAddress></rpCntInfo><role><RoleCd value="005"/></role></distorCont></distributor><distributor xmlns=""><distorOrdPrc><ordInstr>Call (202-366-DATA), or E-mail (answers@bts.gov) BTS to request the National Transportation Atlas Databases (NTAD) 2014 DVD. The NTAD DVD can be ordered from the online bookstore at www.bts.gov. Individual datasets from the NTAD can also be downloaded from the Office of Geospatial Information Systems website at http://www.bts.gov/programs/geographic_information_services/</ordInstr></distorOrdPrc><distorFormat><formatName>ESRI Shapefile</formatName><formatVer>2013</formatVer></distorFormat><distorTran><offLineMed><medName><MedNameCd value="002"/></medName></offLineMed></distorTran><distorTran><onLineSrc><orDesc>National Transportation Atlas Databases (NTAD) 2014</orDesc></onLineSrc></distorTran><distorCont><editorSource>external</editorSource><editorDigest>3b25427eb8f33447a79c28a9cb37e40b</editorDigest><rpOrgName>Office of the Assistant Secretary for Research and Technology/Bureau of Transportation Statistics</rpOrgName><rpCntInfo><cntAddress addressType=""><delPoint>1200 New Jersey Ave. SE</delPoint><city>Washington</city><adminArea>DC</adminArea><postCode>20590</postCode><eMailAdd>answers@BTS.gov</eMailAdd></cntAddress><cntPhone><voiceNum tddtty="">202-366-DATA</voiceNum></cntPhone></rpCntInfo><role><RoleCd value="010"/></role><rpIndName>National Transportation Atlas Database (NTAD) 2014</rpIndName><rpPosName>Geospatial Information Systems</rpPosName><displayName>Research and Innovative Technology Administration/Bureau of Transportation Statistics</displayName><editorSave>True</editorSave><displayName>Office of the Assistant Secretary for Research and Technology/Bureau of Transportation Statistics</displayName></distorCont></distributor><distTranOps xmlns=""><onLineSrc><linkage>http://www.bts.gov/programs/geographic_information_services/</linkage></onLineSrc><transSize Sync="TRUE">0.004</transSize></distTranOps><distFormat xmlns=""><formatName Sync="TRUE">Shapefile</formatName></distFormat></distInfo><dataIdInfo><idCitation><resTitle Sync="FALSE">ports_major v. 2</resTitle><date><pubDate>2013-07-01T00:00:00</pubDate></date><citRespParty xmlns=""><rpOrgName>Waterborne Commerce Statistics Center, US Army Corps of Engineers</rpOrgName><role><RoleCd value="006"/></role></citRespParty><presForm><PresFormCd value="005"/></presForm><presForm><fgdcGeoform>vector digital data</fgdcGeoform></presForm><citRespParty xmlns=""><rpIndName>National Transportation Atlas Database (NTAD) 2014</rpIndName><rpOrgName>Office of the Assistant Secretary for Research and Technology/Bureau of Transportaion Stratistics</rpOrgName><rpPosName>Geospatial Information Systems</rpPosName><rpCntInfo><cntPhone><voiceNum tddtty="">202-366-DATA</voiceNum></cntPhone><cntAddress addressType=""><delPoint>1200 New Jersey Ave. SE</delPoint><city>Washington</city><adminArea>DC</adminArea><postCode>20590</postCode><eMailAdd>answers@BTS.gov</eMailAdd></cntAddress></rpCntInfo><role><RoleCd value="005"/></role><displayName>National Transportation Atlas Database (NTAD) 2013</displayName></citRespParty></idCitation><idAbs>&lt;DIV STYLE="text-align:Left;"&gt;&lt;DIV&gt;&lt;DIV&gt;&lt;P&gt;&lt;SPAN&gt;The ports are politically defined by port limits or Corps projects, excluding non-Corps projects not authorized for publication. The determination for the published Principal Ports is based upon the total tonnage for the port for the particular year; therefore the top 150 list can vary from year to year.&lt;/SPAN&gt;&lt;/P&gt;&lt;/DIV&gt;&lt;/DIV&gt;&lt;/DIV&gt;</idAbs><idPurp>The Principal Port file contains USACE port codes, geographic locations(longitude, latitude), names, and commodity tonnage summaries (total tons, domestic, foreign, imports and exports) for Principal USACE Ports.</idPurp><idCredit>U.S. Army Corps of Engineers, Navigation Data Center, Waterborne Commerce Statistics Center, New Orleans, LA.</idCredit><placeKeys xmlns=""><keyword>spatial</keyword><keyword>US</keyword><keyword>geographic</keyword><keyword>ports</keyword></placeKeys><tempKeys xmlns=""><keyword>2013</keyword><keyword>2014</keyword></tempKeys><themeKeys xmlns=""><keyword>commerce</keyword><keyword>USACE</keyword><keyword>Major Ports</keyword><keyword>Shipping</keyword><keyword>Ports</keyword><keyword>economy</keyword></themeKeys><themeKeys xmlns=""><thesaName xmlns=""><resTitle>ISO 19115 Topic Categories</resTitle></thesaName><keyword>transportation</keyword><keyword>oceans</keyword><keyword>inlandWaters</keyword><keyword>economy</keyword><keyword>structure</keyword><keyword>NGDA</keyword><keyword>Transportation Theme</keyword></themeKeys><searchKeys><keyword>spatial</keyword><keyword>transportation</keyword><keyword>oceans</keyword><keyword>US</keyword><keyword>commerce</keyword><keyword>USACE</keyword><keyword>Major Ports</keyword><keyword>inlandWaters</keyword><keyword>economy</keyword><keyword>structure</keyword><keyword>Shipping</keyword><keyword>geographic</keyword><keyword>Ports</keyword><keyword>ports</keyword><keyword>economy</keyword><keyword>NGDA</keyword><keyword>Transportation Theme</keyword><keyword>2014</keyword></searchKeys><resConst><LegConsts><useLimit>See access and use constraints information.</useLimit></LegConsts></resConst><aggrInfo xmlns=""><aggrDSName xmlns=""><resTitle>National Transportation Atlas Databases (NTAD) 2014</resTitle></aggrDSName><assocType><AscTypeCd value="001"/></assocType></aggrInfo><spatRpType><SpatRepTypCd value="001"/></spatRpType><dataLang><languageCode value="eng"/><countryCode value="USA" Sync="TRUE"/></dataLang><envirDesc Sync="TRUE">Microsoft Windows 7 Version 6.1 (Build 7601) Service Pack 1; Esri ArcGIS 10.1.0.3035</envirDesc><suppInfo>File Format: ASCII Comma Delimited and dBase Maximum Characters per Record: 96 Media: CD, disk, tape, hardcopy</suppInfo><dataChar><CharSetCd value="004"/></dataChar><idPoC xmlns=""><rpOrgName>Waterborne Commerce Statistics Center, US Army Corps of Engineers</rpOrgName><role><RoleCd value="006"/></role><displayName>Waterborne Commerce Statistics Center, US Army Corps of Engineers</displayName></idPoC><resMaint xmlns=""><maintCont xmlns=""><rpIndName>Waterborne Commerce Statistics Center</rpIndName><rpOrgName>US Army Corps of Engineers</rpOrgName><rpCntInfo><cntAddress addressType="both"><city>Vicksburg</city><adminArea>MS</adminArea><country>US</country></cntAddress></rpCntInfo><role><RoleCd value="007"/></role><displayName>Waterborne Commerce Statistics Center</displayName></maintCont></resMaint><dataExt><geoEle xmlns=""><GeoBndBox esriExtentType="search"><exTypeCode Sync="TRUE">1</exTypeCode><westBL Sync="TRUE">-168.938200</westBL><eastBL Sync="TRUE">-66.166670</eastBL><northBL Sync="TRUE">67.719180</northBL><southBL Sync="TRUE">18.001260</southBL></GeoBndBox></geoEle></dataExt><tpCat><TopicCatCd value="018"/></tpCat><tpCat><TopicCatCd value="017"/></tpCat><tpCat><TopicCatCd value="005"/></tpCat><tpCat><TopicCatCd value="012"/></tpCat><tpCat><TopicCatCd value="014"/></tpCat></dataIdInfo><spatRepInfo><VectSpatRep><geometObjs Name="ports_major"><geoObjTyp><GeoObjTypCd value="004" Sync="TRUE"/></geoObjTyp><geoObjCnt Sync="TRUE">150</geoObjCnt></geometObjs><topLvl><TopoLevCd value="001" Sync="TRUE"/></topLvl></VectSpatRep></spatRepInfo><eainfo><detailed Name="ports_major" xmlns=""><enttyp><enttypl Sync="TRUE">ports_major</enttypl><enttypd>150 tops ports</enttypd><enttypds>USACE</enttypds><enttypt Sync="TRUE">Feature Class</enttypt><enttypc Sync="TRUE">150</enttypc></enttyp><attr xmlns=""><attrlabl>FID</attrlabl><attrdef>sequential number</attrdef><attrdefs>esri</attrdefs><attrdomv><udom>Sequential unique whole numbers that are automatically generated.</udom></attrdomv><attalias Sync="TRUE">FID</attalias><attrtype Sync="TRUE">OID</attrtype><attwidth Sync="TRUE">4</attwidth><atprecis Sync="TRUE">0</atprecis><attscale Sync="TRUE">0</attscale></attr><attr xmlns=""><attrlabl>Shape</attrlabl><attrdef>type of geospatial feature</attrdef><attrdefs>esri</attrdefs><attrdomv><edom><edomv>Point</edomv><edomvd>feature type</edomvd><edomvds>esri</edomvds></edom><udom>Coordinates defining the features.</udom></attrdomv><attalias Sync="TRUE">Shape</attalias><attrtype Sync="TRUE">Geometry</attrtype><attwidth Sync="TRUE">0</attwidth><atprecis Sync="TRUE">0</atprecis><attscale Sync="TRUE">0</attscale></attr><attr xmlns=""><attrlabl>PORT</attrlabl><attrdef>USACE assigned port code identifier.</attrdef><attrdefs>USACE</attrdefs><attalias Sync="TRUE">PORT</attalias><attrtype Sync="TRUE">String</attrtype><attwidth Sync="TRUE">5</attwidth><atprecis Sync="TRUE">0</atprecis><attscale Sync="TRUE">0</attscale></attr><attr xmlns=""><attrlabl>LONGITUDE1</attrlabl><attrdef>Longitude</attrdef><attrdefs>USACE</attrdefs><attalias Sync="TRUE">LONGITUDE1</attalias><attrtype Sync="TRUE">Double</attrtype><attwidth Sync="TRUE">15</attwidth><atprecis Sync="TRUE">14</atprecis><attscale Sync="TRUE">6</attscale></attr><attr xmlns=""><attrlabl Sync="TRUE">LATITUDE11</attrlabl><attalias Sync="TRUE">LATITUDE11</attalias><attrtype Sync="TRUE">Double</attrtype><attwidth Sync="TRUE">15</attwidth><atprecis Sync="TRUE">14</atprecis><attscale Sync="TRUE">6</attscale><attrdef>Latitude</attrdef><attrdefs>USACE</attrdefs></attr><attr xmlns=""><attrlabl>PORT_NAME</attrlabl><attrdef>Port name</attrdef><attrdefs>USACE</attrdefs><attalias Sync="TRUE">PORT_NAME</attalias><attrtype Sync="TRUE">String</attrtype><attwidth Sync="TRUE">28</attwidth><atprecis Sync="TRUE">0</atprecis><attscale Sync="TRUE">0</attscale></attr><attr xmlns=""><attrlabl>TOTAL</attrlabl><attrdef>Commidity tonnage total.</attrdef><attrdefs>USACE</attrdefs><attalias Sync="TRUE">TOTAL</attalias><attrtype Sync="TRUE">Double</attrtype><attwidth Sync="TRUE">15</attwidth><atprecis Sync="TRUE">15</atprecis><attscale Sync="TRUE">0</attscale></attr><attr xmlns=""><attrlabl>DOMESTIC</attrlabl><attrdef>Commodity tonnage domestic.</attrdef><attrdefs>USACE</attrdefs><attalias Sync="TRUE">DOMESTIC</attalias><attrtype Sync="TRUE">Double</attrtype><attwidth Sync="TRUE">15</attwidth><atprecis Sync="TRUE">15</atprecis><attscale Sync="TRUE">0</attscale></attr><attr xmlns=""><attrlabl>FOREIGN</attrlabl><attrdef>Commodity tonnage foreign.</attrdef><attrdefs>USACE</attrdefs><attalias Sync="TRUE">FOREIGN</attalias><attrtype Sync="TRUE">Double</attrtype><attwidth Sync="TRUE">15</attwidth><atprecis Sync="TRUE">15</atprecis><attscale Sync="TRUE">0</attscale></attr><attr xmlns=""><attrlabl>IMPORTS</attrlabl><attrdef>Commodity tonnge imports to port.</attrdef><attrdefs>USACE</attrdefs><attalias Sync="TRUE">IMPORTS</attalias><attrtype Sync="TRUE">Double</attrtype><attwidth Sync="TRUE">15</attwidth><atprecis Sync="TRUE">15</atprecis><attscale Sync="TRUE">0</attscale></attr><attr xmlns=""><attrlabl>EXPORTS</attrlabl><attrdef>Commodity tonnage exports from port.</attrdef><attrdefs>USACE</attrdefs><attalias Sync="TRUE">EXPORTS</attalias><attrtype Sync="TRUE">Double</attrtype><attwidth Sync="TRUE">15</attwidth><atprecis Sync="TRUE">15</atprecis><attscale Sync="TRUE">0</attscale></attr><attr xmlns=""><attrlabl>STPOSTAL</attrlabl><attrdef>U.S. Postal Service two letter state abbreviation</attrdef><attrdefs>USPS</attrdefs><attrdomv><codesetd><codesetn>Official List of State Postal Abbreviations</codesetn><codesets>U.S. Postal Service</codesets></codesetd></attrdomv><attalias Sync="TRUE">STPOSTAL</attalias><attrtype Sync="TRUE">String</attrtype><attwidth Sync="TRUE">2</attwidth><atprecis Sync="TRUE">0</atprecis><attscale Sync="TRUE">0</attscale></attr><attr xmlns=""><attrlabl>STFIPS</attrlabl><attrdef>State FIPS code</attrdef><attrdefs>NIST</attrdefs><attrdomv><codesetd><codesetn>Federal Information Processing Standard (FIPS), Publication 6-4</codesetn><codesets>National Institute for Standards and Technology (NIST)</codesets></codesetd></attrdomv><attalias Sync="TRUE">STFIPS</attalias><attrtype Sync="TRUE">String</attrtype><attwidth Sync="TRUE">2</attwidth><atprecis Sync="TRUE">0</atprecis><attscale Sync="TRUE">0</attscale></attr></detailed></eainfo><mdHrLvName Sync="TRUE">dataset</mdHrLvName><refSysInfo><RefSystem dimension=""><refSysID><identCode code="4326" Sync="TRUE" value="4326"/><idCodeSpace Sync="TRUE">EPSG</idCodeSpace><idVersion Sync="TRUE">7.9.4</idVersion></refSysID></RefSystem></refSysInfo><spdoinfo><ptvctinf><esriterm Name="ports_major"><efeatyp Sync="TRUE">Simple</efeatyp><efeageom code="1" Sync="TRUE"/><esritopo Sync="TRUE">FALSE</esritopo><efeacnt Sync="TRUE">150</efeacnt><spindex Sync="TRUE">TRUE</spindex><linrefer Sync="TRUE">FALSE</linrefer></esriterm></ptvctinf></spdoinfo><mdMaint xmlns=""><maintCont xmlns=""><rpIndName>Waterborne Commerce Statistics Center</rpIndName><rpOrgName>US Army Corps of Engineers</rpOrgName><rpCntInfo><cntAddress addressType="both"><city>Vicksburg</city><adminArea>MS</adminArea><country>US</country></cntAddress></rpCntInfo><role><RoleCd value="007"/></role><displayName>Waterborne Commerce Statistics Center</displayName></maintCont></mdMaint><mdContact xmlns=""><editorSource>external</editorSource><editorDigest>3b25427eb8f33447a79c28a9cb37e40b</editorDigest><rpOrgName>Office of the Assistant Secretary for Research and Technology/Bureau of Transportation Statistics</rpOrgName><rpCntInfo><cntAddress addressType=""><delPoint>1200 New Jersey Ave. SE</delPoint><city>Washington</city><adminArea>DC</adminArea><postCode>20590</postCode><eMailAdd>answers@BTS.gov</eMailAdd></cntAddress><cntPhone><voiceNum tddtty="">202-366-DATA</voiceNum></cntPhone></rpCntInfo><role><RoleCd value="010"/></role><rpIndName>National Transportation Atlas Database (NTAD) 2014</rpIndName><rpPosName>Geospatial Information Systems</rpPosName><displayName>Research and Innovative Technology Administration/Bureau of Transportation Statistics</displayName><editorSave>True</editorSave><displayName>Office of the Assistant Secretary for Research and Technology/Bureau of Transportation Statistics</displayName></mdContact></metadata>
